compare_old_and_new_entry.py
ebay_email_tracker.py
email_module.py
misc_module.py
scrape_get_data.py
user_prompt.py
wait_module.py
eBay_email_tracker-0.0.4.dist-info/METADATA
eBay_email_tracker-0.0.4.dist-info/WHEEL
eBay_email_tracker-0.0.4.dist-info/top_level.txt
eBay_email_tracker-0.0.4.dist-info/RECORD
