Metadata-Version: 2.1
Name: eBay-email-tracker
Version: 0.0.4
Summary: Scapes an entire search page of a particular item on eBay and sends regular updates to an email address
Home-page: UNKNOWN
License: UNKNOWN
Platform: UNKNOWN
Classifier: Programming Language :: Python :: 3
Classifier: Programming Language :: Python :: 3.9
Classifier: Programming Language :: Python :: 3.10
Requires-Dist: pandas (~=1.3.5)
Requires-Dist: numpy (~=1.22.0)
Requires-Dist: requests (~=2.27.1)
Requires-Dist: beautifulsoup4 (~=4.10.0)
Requires-Dist: lxml (~=4.7.1)
Provides-Extra: dev
Requires-Dist: pytest (>=3.7) ; extra == 'dev'
